{
	"name": "pl_silver_standardization",
	"properties": {
		"description": "Silver layer standardization pipeline for all source systems (CRM, ERP, Reference, Weather, Web)",
		"activities": [
			{
				"name": "nb_silver_crm_clients",
				"description": "Run Silver standardization notebook for CRM clients",
				"type": "DatabricksNotebook",
				"dependsOn": [],
				"policy": {
					"timeout": "0.12:00:00",
					"retry": 1,
					"retryIntervalInSeconds": 30,
					"secureOutput": false,
					"secureInput": false
				},
				"userProperties": [],
				"typeProperties": {
					"notebookPath": "/pt_frozen_foods_251201/03_silver/processing/crm/silver_crm_clients"
				},
				"linkedServiceName": {
					"referenceName": "ls_databricks_ptfrozenfoods_dev",
					"type": "LinkedServiceReference"
				}
			},
			{
				"name": "nb_silver_crm_segmentation",
				"description": "Run Silver standardization notebook for CRM segmentation",
				"type": "DatabricksNotebook",
				"dependsOn": [
					{
						"activity": "nb_silver_crm_clients",
						"dependencyConditions": [
							"Succeeded"
						]
					}
				],
				"policy": {
					"timeout": "0.12:00:00",
					"retry": 1,
					"retryIntervalInSeconds": 30,
					"secureOutput": false,
					"secureInput": false
				},
				"userProperties": [],
				"typeProperties": {
					"notebookPath": "/pt_frozen_foods_251201/03_silver/processing/crm/silver_crm_segmentation"
				},
				"linkedServiceName": {
					"referenceName": "ls_databricks_ptfrozenfoods_dev",
					"type": "LinkedServiceReference"
				}
			},
			{
				"name": "nb_silver_crm_status",
				"description": "Run Silver standardization notebook for CRM status",
				"type": "DatabricksNotebook",
				"dependsOn": [
					{
						"activity": "nb_silver_crm_segmentation",
						"dependencyConditions": [
							"Succeeded"
						]
					}
				],
				"policy": {
					"timeout": "0.12:00:00",
					"retry": 1,
					"retryIntervalInSeconds": 30,
					"secureOutput": false,
					"secureInput": false
				},
				"userProperties": [],
				"typeProperties": {
					"notebookPath": "/pt_frozen_foods_251201/03_silver/processing/crm/silver_crm_status"
				},
				"linkedServiceName": {
					"referenceName": "ls_databricks_ptfrozenfoods_dev",
					"type": "LinkedServiceReference"
				}
			},
			{
				"name": "nb_silver_erp_orders",
				"description": "Run Silver standardization notebook for ERP orders",
				"type": "DatabricksNotebook",
				"dependsOn": [
					{
						"activity": "nb_silver_crm_status",
						"dependencyConditions": [
							"Succeeded"
						]
					}
				],
				"policy": {
					"timeout": "0.12:00:00",
					"retry": 1,
					"retryIntervalInSeconds": 30,
					"secureOutput": false,
					"secureInput": false
				},
				"userProperties": [],
				"typeProperties": {
					"notebookPath": "/pt_frozen_foods_251201/03_silver/processing/erp/silver_erp_orders"
				},
				"linkedServiceName": {
					"referenceName": "ls_databricks_ptfrozenfoods_dev",
					"type": "LinkedServiceReference"
				}
			},
			{
				"name": "nb_silver_erp_order_items",
				"description": "Run Silver standardization notebook for ERP order items",
				"type": "DatabricksNotebook",
				"dependsOn": [
					{
						"activity": "nb_silver_erp_orders",
						"dependencyConditions": [
							"Succeeded"
						]
					}
				],
				"policy": {
					"timeout": "0.12:00:00",
					"retry": 1,
					"retryIntervalInSeconds": 30,
					"secureOutput": false,
					"secureInput": false
				},
				"userProperties": [],
				"typeProperties": {
					"notebookPath": "/pt_frozen_foods_251201/03_silver/processing/erp/silver_erp_order_items"
				},
				"linkedServiceName": {
					"referenceName": "ls_databricks_ptfrozenfoods_dev",
					"type": "LinkedServiceReference"
				}
			},
			{
				"name": "nb_silver_erp_products",
				"description": "Run Silver standardization notebook for ERP products",
				"type": "DatabricksNotebook",
				"dependsOn": [
					{
						"activity": "nb_silver_erp_order_items",
						"dependencyConditions": [
							"Succeeded"
						]
					}
				],
				"policy": {
					"timeout": "0.12:00:00",
					"retry": 2,
					"retryIntervalInSeconds": 30,
					"secureOutput": false,
					"secureInput": false
				},
				"userProperties": [],
				"typeProperties": {
					"notebookPath": "/pt_frozen_foods_251201/03_silver/processing/erp/silver_erp_products"
				},
				"linkedServiceName": {
					"referenceName": "ls_databricks_ptfrozenfoods_dev",
					"type": "LinkedServiceReference"
				}
			},
			{
				"name": "nb_silver_erp_salespersons",
				"description": "Run Silver standardization notebook for ERP salespersons",
				"type": "DatabricksNotebook",
				"dependsOn": [
					{
						"activity": "nb_silver_erp_products",
						"dependencyConditions": [
							"Succeeded"
						]
					}
				],
				"policy": {
					"timeout": "0.12:00:00",
					"retry": 1,
					"retryIntervalInSeconds": 30,
					"secureOutput": false,
					"secureInput": false
				},
				"userProperties": [],
				"typeProperties": {
					"notebookPath": "/pt_frozen_foods_251201/03_silver/processing/erp/silver_erp_salespersons"
				},
				"linkedServiceName": {
					"referenceName": "ls_databricks_ptfrozenfoods_dev",
					"type": "LinkedServiceReference"
				}
			},
			{
				"name": "nb_silver_erp_suppliers",
				"description": "Run Silver standardization notebook for ERP suppliers",
				"type": "DatabricksNotebook",
				"dependsOn": [
					{
						"activity": "nb_silver_erp_salespersons",
						"dependencyConditions": [
							"Succeeded"
						]
					}
				],
				"policy": {
					"timeout": "0.12:00:00",
					"retry": 1,
					"retryIntervalInSeconds": 30,
					"secureOutput": false,
					"secureInput": false
				},
				"userProperties": [],
				"typeProperties": {
					"notebookPath": "/pt_frozen_foods_251201/03_silver/processing/erp/silver_erp_suppliers"
				},
				"linkedServiceName": {
					"referenceName": "ls_databricks_ptfrozenfoods_dev",
					"type": "LinkedServiceReference"
				}
			},
			{
				"name": "nb_silver_reference_calendar",
				"description": "Run Silver standardization notebook for reference calendar",
				"type": "DatabricksNotebook",
				"dependsOn": [
					{
						"activity": "nb_silver_erp_suppliers",
						"dependencyConditions": [
							"Succeeded"
						]
					}
				],
				"policy": {
					"timeout": "0.12:00:00",
					"retry": 1,
					"retryIntervalInSeconds": 30,
					"secureOutput": false,
					"secureInput": false
				},
				"userProperties": [],
				"typeProperties": {
					"notebookPath": "/pt_frozen_foods_251201/03_silver/processing/reference/silver_reference_calendar"
				},
				"linkedServiceName": {
					"referenceName": "ls_databricks_ptfrozenfoods_dev",
					"type": "LinkedServiceReference"
				}
			},
			{
				"name": "nb_silver_reference_locations",
				"description": "Run Silver standardization notebook for reference locations",
				"type": "DatabricksNotebook",
				"dependsOn": [
					{
						"activity": "nb_silver_reference_calendar",
						"dependencyConditions": [
							"Succeeded"
						]
					}
				],
				"policy": {
					"timeout": "0.12:00:00",
					"retry": 1,
					"retryIntervalInSeconds": 30,
					"secureOutput": false,
					"secureInput": false
				},
				"userProperties": [],
				"typeProperties": {
					"notebookPath": "/pt_frozen_foods_251201/03_silver/processing/reference/silver_reference_locations"
				},
				"linkedServiceName": {
					"referenceName": "ls_databricks_ptfrozenfoods_dev",
					"type": "LinkedServiceReference"
				}
			},
			{
				"name": "nb_silver_reference_sales_channels",
				"description": "Run Silver standardization notebook for reference sales channels",
				"type": "DatabricksNotebook",
				"dependsOn": [
					{
						"activity": "nb_silver_reference_locations",
						"dependencyConditions": [
							"Succeeded"
						]
					}
				],
				"policy": {
					"timeout": "0.12:00:00",
					"retry": 1,
					"retryIntervalInSeconds": 30,
					"secureOutput": false,
					"secureInput": false
				},
				"userProperties": [],
				"typeProperties": {
					"notebookPath": "/pt_frozen_foods_251201/03_silver/processing/reference/silver_reference_sales_channels"
				},
				"linkedServiceName": {
					"referenceName": "ls_databricks_ptfrozenfoods_dev",
					"type": "LinkedServiceReference"
				}
			},
			{
				"name": "nb_silver_weather_porto_daily",
				"description": "Run Silver standardization notebook for Porto daily weather data",
				"type": "DatabricksNotebook",
				"dependsOn": [
					{
						"activity": "nb_silver_reference_sales_channels",
						"dependencyConditions": [
							"Succeeded"
						]
					}
				],
				"policy": {
					"timeout": "0.12:00:00",
					"retry": 2,
					"retryIntervalInSeconds": 30,
					"secureOutput": false,
					"secureInput": false
				},
				"userProperties": [],
				"typeProperties": {
					"notebookPath": "/pt_frozen_foods_251201/03_silver/processing/weather_api/silver_weather_api_weather_porto_daily"
				},
				"linkedServiceName": {
					"referenceName": "ls_databricks_ptfrozenfoods_dev",
					"type": "LinkedServiceReference"
				}
			},
			{
				"name": "nb_silver_web_event_logs",
				"description": "Run Silver standardization notebook for web event logs",
				"type": "DatabricksNotebook",
				"dependsOn": [
					{
						"activity": "nb_silver_weather_porto_daily",
						"dependencyConditions": [
							"Succeeded"
						]
					}
				],
				"policy": {
					"timeout": "0.12:00:00",
					"retry": 1,
					"retryIntervalInSeconds": 30,
					"secureOutput": false,
					"secureInput": false
				},
				"userProperties": [],
				"typeProperties": {
					"notebookPath": "/pt_frozen_foods_251201/03_silver/processing/web/silver_web_web_event_logs"
				},
				"linkedServiceName": {
					"referenceName": "ls_databricks_ptfrozenfoods_dev",
					"type": "LinkedServiceReference"
				}
			}
		],
		"annotations": []
	}
}