{
  "$schema": "https://developer.microsoft.com/json-schemas/fabric/item/report/definition/visualContainer/2.8.0/schema.json",
  "name": "f2cc8f49ef7a1894cbf2",
  "position": {
    "x": 918.34726534511583,
    "y": 0,
    "z": 4000,
    "height": 102.71793647002627,
    "width": 361.95844279914019,
    "tabOrder": 4000
  },
  "visual": {
    "visualType": "slicer",
    "query": {
      "queryState": {
        "Values": {
          "projections": [
            {
              "field": {
                "Column": {
                  "Expression": {
                    "SourceRef": {
                      "Entity": "analytics_sales_overview"
                    }
                  },
                  "Property": "data_pedido"
                }
              },
              "queryRef": "analytics_sales_overview.data_pedido",
              "nativeQueryRef": "data_pedido",
              "active": true
            }
          ]
        }
      },
      "sortDefinition": {
        "sort": [
          {
            "field": {
              "Column": {
                "Expression": {
                  "SourceRef": {
                    "Entity": "analytics_sales_overview"
                  }
                },
                "Property": "data_pedido"
              }
            },
            "direction": "Ascending"
          }
        ],
        "isDefaultSort": true
      }
    },
    "objects": {
      "data": [
        {
          "properties": {
            "startDate": {
              "expr": {
                "Literal": {
                  "Value": "datetime'2021-01-11T00:00:00'"
                }
              }
            },
            "endDate": {
              "expr": {
                "Literal": {
                  "Value": "datetime'2026-01-25T00:00:00'"
                }
              }
            },
            "mode": {
              "expr": {
                "Literal": {
                  "Value": "'Between'"
                }
              }
            }
          }
        }
      ],
      "general": [
        {
          "properties": {
            "orientation": {
              "expr": {
                "Literal": {
                  "Value": "1D"
                }
              }
            },
            "outlineColor": {
              "solid": {
                "color": {
                  "expr": {
                    "ThemeDataColor": {
                      "ColorId": 2,
                      "Percent": 0
                    }
                  }
                }
              }
            },
            "outlineWeight": {
              "expr": {
                "Literal": {
                  "Value": "1D"
                }
              }
            },
            "filter": {
              "filter": {
                "Version": 2,
                "From": [
                  {
                    "Name": "a",
                    "Entity": "analytics_sales_overview",
                    "Type": 0
                  }
                ],
                "Where": [
                  {
                    "Condition": {
                      "And": {
                        "Left": {
                          "Comparison": {
                            "ComparisonKind": 2,
                            "Left": {
                              "Column": {
                                "Expression": {
                                  "SourceRef": {
                                    "Source": "a"
                                  }
                                },
                                "Property": "data_pedido"
                              }
                            },
                            "Right": {
                              "Literal": {
                                "Value": "datetime'2021-01-11T00:00:00'"
                              }
                            }
                          }
                        },
                        "Right": {
                          "Comparison": {
                            "ComparisonKind": 3,
                            "Left": {
                              "Column": {
                                "Expression": {
                                  "SourceRef": {
                                    "Source": "a"
                                  }
                                },
                                "Property": "data_pedido"
                              }
                            },
                            "Right": {
                              "Literal": {
                                "Value": "datetime'2026-01-26T00:00:00'"
                              }
                            }
                          }
                        }
                      }
                    }
                  }
                ]
              }
            }
          }
        }
      ],
      "date": [
        {
          "properties": {
            "bold": {
              "expr": {
                "Literal": {
                  "Value": "false"
                }
              }
            },
            "italic": {
              "expr": {
                "Literal": {
                  "Value": "true"
                }
              }
            },
            "underline": {
              "expr": {
                "Literal": {
                  "Value": "false"
                }
              }
            },
            "textSize": {
              "expr": {
                "Literal": {
                  "Value": "12D"
                }
              }
            },
            "fontColor": {
              "solid": {
                "color": {
                  "expr": {
                    "ThemeDataColor": {
                      "ColorId": 1,
                      "Percent": 0
                    }
                  }
                }
              }
            }
          }
        }
      ],
      "header": [
        {
          "properties": {
            "textSize": {
              "expr": {
                "Literal": {
                  "Value": "14D"
                }
              }
            },
            "text": {
              "expr": {
                "Literal": {
                  "Value": "'Period Filter'"
                }
              }
            }
          }
        }
      ]
    },
    "syncGroup": {
      "groupName": "data_pedido",
      "fieldChanges": true,
      "filterChanges": true
    },
    "drillFilterOtherVisuals": true
  }
}